macros/multiplexer/verilog/src/multiplexer.v
// Copyright 2025 Simon Dorrer
//
// Licensed under the Apache License, Version 2.0 (the "License");
// you may not use this file except in compliance with the License.
// You may obtain a copy of the License at
//
// http://www.apache.org/licenses/LICENSE−2.0
//
// Unless required by applicable law or agreed to in writing, software
// distributed under the License is distributed on an "AS IS" BASIS,
// WITHOUT WARRANTIES OR CONDITIONS OF ANY KIND, either express or implied.
// See the License for the specific language governing permissions and
// limitations under the License.

`default_nettype none

module multiplexer (
	input  wire        clk,      		// clock
	
	// Multiplexer - Interface to Pad-Ring
	input  wire [2:0]  design_sel_in, 	// design select (3 bits)
	// Note that only the outputs of the projects are muxed.
	// The inputs of the projects are connected in parallel.
	// Meaning that all projects are running simultaneously, but only the outputs of one project are observed.
	// After a project switch with "design_sel_in" a reset is recommended.
	// input  wire [11:0] mux_in,			// 12 inputs for all projects
	output  wire [10:0] mux_out,			// 11 outputs for all projects
	
	// TinyBF
	// output wire [3:0] uo_out,			// TinyBF: input  wire [3:0] ui_in
	input  wire [3:0] uio_in,				// TinyBF: output wire [3:0] uio_out
    input  wire [6:0] ui_in,				// TinyBF: output wire [6:0] uo_out
	
	// SAR ADC Controller
	// output wire start_out,				// SAR ADC Controller: input wire start
	// output wire comp_out,				// SAR ADC Controller: input wire comp_in
	input  wire [7:0] dac_bits_in,			// SAR ADC Controller: output wire [7:0] dac_bits
	input  wire spi_miso_in,				// SAR ADC Controller: output wire spi_miso
	input  wire spi_sclk_in,				// SAR ADC Controller: output wire spi_sclk
	input  wire done_in,					// SAR ADC Controller: output wire done
	
	// Led Spinner
	// output wire [3:0] speed_bits_out,	// Led Spinner: input  wire [3:0] speed_bits_in
	// output wire       stop_wheel_out,	// Led Spinner: input  wire       stop_wheel_in
	// output wire [5:0] guess_bits_out,	// Led Spinner: input  wire [5:0] guess_bits_in
	input  wire [6:0] seg_bits_in,			// Led Spinner: output wire [6:0] seg_bits_out
	input  wire		  dp_on_in,				// Led Spinner: output wire		  dp_on_out
	
	// TinyToneGen
	// output wire       ena_out,			// TinyToneGen: input  wire       ena
	// output wire [2:0] address_out,		// TinyToneGen: input  wire [2:0] address_in  
	// output wire 	  write_strobe_out,		// TinyToneGen: input  wire 	  write_strobe_in  
	// output wire [4:0] data_out,			// TinyToneGen: input  wire [4:0] data_in
	input  wire 	  signal_bit_in,		// TinyToneGen: output wire 	  signal_bit_out
	
	// Digital Filter
	// output wire 	  enconfig_out, 		// Digital Filter: input wire enconfig
	// output wire [2:0] config_out, 		// Digital Filter: input wire [2:0] configin
	// output wire [7:0] data_out, 			// Digital Filter: input wire [7:0] datain
	input  wire [7:0] data_in,				// Digital Filter: output wire [7:0] dataout
	
	// Traffic Light Controller
	// output wire switch_traffic_light_on_out, // Traffic Light Controller: input  wire switch_traffic_light_on_in
    // output wire ped_request_left_out, 		// Traffic Light Controller: input  wire ped_request_left_in
    // output wire ped_request_right_out, 		// Traffic Light Controller: input  wire ped_request_right_in
    input  wire car_red_light_in, 				// Traffic Light Controller: output wire car_red_light_out
	input  wire car_yellow_light_in, 			// Traffic Light Controller: output wire car_yellow_light_out
	input  wire car_green_light_in, 			// Traffic Light Controller: output wire car_green_light_out
	input  wire ped_red_light_in, 				// Traffic Light Controller: output wire ped_red_light_out
	input  wire ped_green_light_in, 			// Traffic Light Controller: output wire ped_green_light_out
	input  wire DIN_in, 						// Traffic Light Controller: output wire DIN_out
	input  wire CS_in, 							// Traffic Light Controller: output wire CS_out
	input  wire SCLK_in, 						// Traffic Light Controller: output wire SCLK_out
	input  wire pushed_left_in, 				// Traffic Light Controller: output wire pushed_left_out
	input  wire pushed_right_in, 				// Traffic Light Controller: output wire pushed_right_out
	
	// Tetris
	// output up_r_o, 							// Tetris: input  up_r_i
	// output down_r_o, 						// Tetris: input  down_r_i
	// output left_r_o, 						// Tetris: input  left_r_i
	// output right_r_o, 						// Tetris: input  right_r_i
	// output game_speed_o, 					// Tetris: input  game_speed_i
	input  wire [5:0] Data_i, 					// Tetris: output [5:0] Data_o
	input  wire hsync_i, 						// Tetris: output hsync_o
	input  wire vsync_i, 						// Tetris: output vsync_o
	input  wire video_active_i, 				// Tetris: output video_active_o
	input  wire pix_clk_i, 						// Tetris: output pix_clk_o
	
	// Classic VGA Clock
    // output wire hour_out, 					// Classic VGA Clock: input wire hour_in
    // output wire min_out, 					// Classic VGA Clock: input wire min_in
    // output wire sec_out, 					// Classic VGA Clock: input wire sec_in
    // output wire al_out, 						// Classic VGA Clock: input wire al_in
    // output wire al_on_off_toggle_out, 		// Classic VGA Clock: input wire al_on_off_toggle_in
    input  wire buzzer_in, 						// Classic VGA Clock: output wire buzzer_out
    input  wire vga_horizSync_in, 				// Classic VGA Clock: output wire vga_horizSync_out
    input  wire vga_vertSync_in, 				// Classic VGA Clock: output wire vga_vertSync_out
    input  wire black_white_in 					// Classic VGA Clock: output wire black_white_out
);
	
	// Register for Outputs
	reg [10:0] mux_out_reg;
	
	// MUX
	always @(*) begin
		case(design_sel_in)
			default: begin
				mux_out_reg[10:0] = 11'b00000000000;
			end
			// TinyBF
			3'b000: begin
				mux_out_reg[10:7] = uio_in;
				mux_out_reg[6:0]  = ui_in;
			end
			// SAR ADC Controller
			3'b001: begin
				mux_out_reg[10]   = spi_miso_in;
				mux_out_reg[9] 	  = spi_sclk_in;
				mux_out_reg[8] 	  = done_in;
				mux_out_reg[7:0]  = dac_bits_in;
			end
			// Led Spinner
			3'b010: begin
				mux_out_reg[10:8] = 3'b000;
				mux_out_reg[7] 	  = dp_on_in;
				mux_out_reg[6:0]  = seg_bits_in;
			end
			// TinyToneGen
			3'b011: begin
				mux_out_reg[10:1] = 10'b0000000000;
				mux_out_reg[0] 	  = signal_bit_in;
			end
			// Digital Filter
			3'b100: begin
				mux_out_reg[10:8] = 3'b000;
				mux_out_reg[7:0]  = data_in;
			end
			// Traffic Light Controller
			3'b101: begin
				mux_out_reg[10]   = 1'b0;
				mux_out_reg[9]    = car_red_light_in;
				mux_out_reg[8]    = car_yellow_light_in;
				mux_out_reg[7]    = car_green_light_in;
				mux_out_reg[6]    = ped_red_light_in;
				mux_out_reg[5]    = ped_green_light_in;
				mux_out_reg[4]    = DIN_in;
				mux_out_reg[3]    = CS_in;
				mux_out_reg[2]    = SCLK_in;
				mux_out_reg[1]    = pushed_left_in;
				mux_out_reg[0]    = pushed_right_in;
			end
			// Tetris
			3'b110: begin
				mux_out_reg[10]   = 1'b0;
				mux_out_reg[9] 	  = pix_clk_i;
				mux_out_reg[8] 	  = video_active_i;
				mux_out_reg[7] 	  = vsync_i;
				mux_out_reg[6] 	  = hsync_i;
				mux_out_reg[5:0]  = Data_i; 
			end
			// Classic VGA Clock
			3'b111: begin
				mux_out_reg[10:4] = 7'b0000000;
				mux_out_reg[3] 	  = buzzer_in;
				mux_out_reg[2] 	  = vga_horizSync_in;
				mux_out_reg[1] 	  = vga_vertSync_in;
				mux_out_reg[0] 	  = black_white_in;
			end
		endcase
	end
	
	// Assign Registers to Outputs
	assign mux_out = mux_out_reg;
endmodule

macros/multiplexer/verilog/tb/multiplexer_tb.v
// Copyright 2025 Simon Dorrer
//
// Licensed under the Apache License, Version 2.0 (the "License");
// you may not use this file except in compliance with the License.
// You may obtain a copy of the License at
//
// http://www.apache.org/licenses/LICENSE−2.0
//
// Unless required by applicable law or agreed to in writing, software
// distributed under the License is distributed on an "AS IS" BASIS,
// WITHOUT WARRANTIES OR CONDITIONS OF ANY KIND, either express or implied.
// See the License for the specific language governing permissions and
// limitations under the License.

`timescale 1ns/1ns

module multiplexer_tb;

  // inputs
  reg  clk       			= 1'b0; // 25 MHz
  reg  [2:0] design_sel_in  = 3'b000;
  wire [3:0] uio_in			= 4'b1111;
  wire [6:0] ui_in			= 7'b1111111;
  wire [7:0]dac_bits_in		= 8'b11111111;
  wire spi_miso_in			= 1'b1;
  wire spi_sclk_in			= 1'b1;
  wire done_in				= 1'b1;
  wire [6:0] seg_bits_in	= 7'b1111111;
  wire dp_on_in				= 1'b1;
  wire signal_bit_in 		= 1'b1;
  wire [7:0] data_in		= 8'b11111111;
  wire car_red_light_in		= 1'b1;
  wire car_yellow_light_in	= 1'b1;
  wire car_green_light_in	= 1'b1;
  wire ped_red_light_in		= 1'b1;
  wire ped_green_light_in	= 1'b1;
  wire DIN_in				= 1'b1;
  wire CS_in				= 1'b1;
  wire SCLK_in				= 1'b1;
  wire pushed_left_in		= 1'b1;
  wire pushed_right_in		= 1'b1;
  wire [5:0] Data_i			= 6'b111111;
  wire hsync_i 				= 1'b1;
  wire vsync_i 				= 1'b1;
  wire video_active_i 		= 1'b1;
  wire pix_clk_i 			= 1'b1;			
  wire buzzer_in 			= 1'b1;
  wire vga_horizSync_in		= 1'b1;
  wire vga_vertSync_in		= 1'b1;
  wire black_white_in		= 1'b1;

  // outputs
  wire [10:0] mux_out;

  // dut
  multiplexer dut (
    .clk(clk),
    .design_sel_in(design_sel_in),
	.mux_out(mux_out),
	.uio_in(uio_in),
	.ui_in(ui_in),
	.dac_bits_in(dac_bits_in),
	.spi_miso_in(spi_miso_in),
	.spi_sclk_in(spi_sclk_in),
	.done_in(done_in),
	.seg_bits_in(seg_bits_in),
	.dp_on_in(dp_on_in),
	.signal_bit_in(signal_bit_in),
	.data_in(data_in),
	.car_red_light_in(car_red_light_in),
	.car_yellow_light_in(car_yellow_light_in),
	.car_green_light_in(car_green_light_in),
	.ped_red_light_in(ped_red_light_in),
	.ped_green_light_in(ped_green_light_in),
	.DIN_in(DIN_in),
	.CS_in(CS_in),
	.SCLK_in(SCLK_in),
	.pushed_left_in(pushed_left_in),
	.pushed_right_in(pushed_right_in),
	.Data_i(Data_i),
	.hsync_i(hsync_i),
	.vsync_i(vsync_i),
	.video_active_i(video_active_i),
	.pix_clk_i(pix_clk_i),
	.buzzer_in(buzzer_in),
	.vga_horizSync_in(vga_horizSync_in),
	.vga_vertSync_in(vga_vertSync_in),
	.black_white_in(black_white_in)
  );

  // 25 MHz Clock
  /* verilator lint_off STMTDLY */
  always #20 clk = ~clk;
  /* verilator lint_on STMTDLY */

  initial begin
    $dumpfile("multiplexer_tb.vcd");
    $dumpvars(0, multiplexer_tb);
    $dumpvars(0, multiplexer_tb.dut);
	
	#200
	design_sel_in  = 3'b001;
	
	#200
	design_sel_in  = 3'b010;
	
	#200
	design_sel_in  = 3'b011;
	
	#200
	design_sel_in  = 3'b100;
	
	#200
	design_sel_in  = 3'b101;
	
	#200
	design_sel_in  = 3'b110;
	
	#200
	design_sel_in  = 3'b111;
	
    #200 $finish;
    /* verilator lint_on STMTDLY */
  end
endmodule

macros/multiplexer/verilog/tb/multiplexer_tb.vcd
$date
	Mon Dec  1 14:00:05 2025
$end
$version
	Icarus Verilog
$end
$timescale
	1ns
$end
$scope module multiplexer_tb $end
$var wire 1 ! CS_in $end
$var wire 1 " DIN_in $end
$var wire 6 # Data_i [5:0] $end
$var wire 1 $ SCLK_in $end
$var wire 1 % black_white_in $end
$var wire 1 & buzzer_in $end
$var wire 1 ' car_green_light_in $end
$var wire 1 ( car_red_light_in $end
$var wire 1 ) car_yellow_light_in $end
$var wire 8 * dac_bits_in [7:0] $end
$var wire 8 + data_in [7:0] $end
$var wire 1 , done_in $end
$var wire 1 - dp_on_in $end
$var wire 1 . hsync_i $end
$var wire 1 / ped_green_light_in $end
$var wire 1 0 ped_red_light_in $end
$var wire 1 1 pix_clk_i $end
$var wire 1 2 pushed_left_in $end
$var wire 1 3 pushed_right_in $end
$var wire 7 4 seg_bits_in [6:0] $end
$var wire 1 5 signal_bit_in $end
$var wire 1 6 spi_miso_in $end
$var wire 1 7 spi_sclk_in $end
$var wire 7 8 ui_in [6:0] $end
$var wire 4 9 uio_in [3:0] $end
$var wire 1 : vga_horizSync_in $end
$var wire 1 ; vga_vertSync_in $end
$var wire 1 < video_active_i $end
$var wire 1 = vsync_i $end
$var wire 11 > mux_out [10:0] $end
$var reg 1 ? clk $end
$var reg 3 @ design_sel_in [2:0] $end
$scope module dut $end
$var wire 1 ! CS_in $end
$var wire 1 " DIN_in $end
$var wire 6 A Data_i [5:0] $end
$var wire 1 $ SCLK_in $end
$var wire 1 % black_white_in $end
$var wire 1 & buzzer_in $end
$var wire 1 ' car_green_light_in $end
$var wire 1 ( car_red_light_in $end
$var wire 1 ) car_yellow_light_in $end
$var wire 1 ? clk $end
$var wire 8 B dac_bits_in [7:0] $end
$var wire 8 C data_in [7:0] $end
$var wire 3 D design_sel_in [2:0] $end
$var wire 1 , done_in $end
$var wire 1 - dp_on_in $end
$var wire 1 . hsync_i $end
$var wire 11 E mux_out [10:0] $end
$var wire 1 / ped_green_light_in $end
$var wire 1 0 ped_red_light_in $end
$var wire 1 1 pix_clk_i $end
$var wire 1 2 pushed_left_in $end
$var wire 1 3 pushed_right_in $end
$var wire 7 F seg_bits_in [6:0] $end
$var wire 1 5 signal_bit_in $end
$var wire 1 6 spi_miso_in $end
$var wire 1 7 spi_sclk_in $end
$var wire 7 G ui_in [6:0] $end
$var wire 4 H uio_in [3:0] $end
$var wire 1 : vga_horizSync_in $end
$var wire 1 ; vga_vertSync_in $end
$var wire 1 < video_active_i $end
$var wire 1 = vsync_i $end
$var reg 11 I mux_out_reg [10:0] $end
$upscope $end
$upscope $end
$scope module multiplexer_tb $end
$scope module dut $end
$upscope $end
$upscope $end
$enddefinitions $end
$comment Show the parameter values. $end
$dumpall
$end
#0
$dumpvars
b11111111111 I
b1111 H
b1111111 G
b1111111 F
b11111111111 E
b0 D
b11111111 C
b11111111 B
b111111 A
b0 @
0?
b11111111111 >
1=
1<
1;
1:
b1111 9
b1111111 8
17
16
15
b1111111 4
13
12
11
10
1/
1.
1-
1,
b11111111 +
b11111111 *
1)
1(
1'
1&
1%
1$
b111111 #
1"
1!
$end
#20
1?
#40
0?
#60
1?
#80
0?
#100
1?
#120
0?
#140
1?
#160
0?
#180
1?
#200
0?
b1 @
b1 D
#220
1?
#240
0?
#260
1?
#280
0?
#300
1?
#320
0?
#340
1?
#360
0?
#380
1?
#400
b11111111 >
b11111111 E
b11111111 I
0?
b10 @
b10 D
#420
1?
#440
0?
#460
1?
#480
0?
#500
1?
#520
0?
#540
1?
#560
0?
#580
1?
#600
b1 >
b1 E
b1 I
0?
b11 @
b11 D
#620
1?
#640
0?
#660
1?
#680
0?
#700
1?
#720
0?
#740
1?
#760
0?
#780
1?
#800
b11111111 >
b11111111 E
b11111111 I
0?
b100 @
b100 D
#820
1?
#840
0?
#860
1?
#880
0?
#900
1?
#920
0?
#940
1?
#960
0?
#980
1?
#1000
b1111111111 >
b1111111111 E
b1111111111 I
0?
b101 @
b101 D
#1020
1?
#1040
0?
#1060
1?
#1080
0?
#1100
1?
#1120
0?
#1140
1?
#1160
0?
#1180
1?
#1200
0?
b110 @
b110 D
#1220
1?
#1240
0?
#1260
1?
#1280
0?
#1300
1?
#1320
0?
#1340
1?
#1360
0?
#1380
1?
#1400
b1111 >
b1111 E
b1111 I
0?
b111 @
b111 D
